neuroarch-0.4.3-py3.7-nspkg.pth
neuroarch/LPU_loader.py
neuroarch/apply_diff.py
neuroarch/diff.py
neuroarch/gen_generic_lpu.py
neuroarch/models.py
neuroarch/na.py
neuroarch/nk.py
neuroarch/nk_direct.py
neuroarch/nxtools.py
neuroarch/query.py
neuroarch/utils.py
neuroarch/version.py
neuroarch/vis.py
neuroarch/conv/__init__.py
neuroarch/conv/nx.py
neuroarch/conv/pd.py
neuroarch/conv/utils.py
neuroarch-0.4.3.dist-info/AUTHORS.rst
neuroarch-0.4.3.dist-info/LICENSE.rst
neuroarch-0.4.3.dist-info/METADATA
neuroarch-0.4.3.dist-info/WHEEL
neuroarch-0.4.3.dist-info/namespace_packages.txt
neuroarch-0.4.3.dist-info/top_level.txt
neuroarch-0.4.3.dist-info/RECORD
