Metadata-Version: 2.1
Name: neuroarch
Version: 0.4.3
Summary: A graph-based platform for representing Drosophila brain architectures
Home-page: https://github.com/fruitflybrain/neuroarch/
Author: Lev Givon, Nikul Ukani, Yiyin Zhou
Author-email: lev@columbia.edu, nikul@ee.columbia.edu, yiyin@ee.columbia.edu
Maintainer: Yiyin Zhou
Maintainer-email: yiyin@ee.columbia.edu
License: BSD
Classifier: Development Status :: 3 - Alpha
Classifier: Intended Audience :: Developers
Classifier: Intended Audience :: Science/Research
Classifier: License :: OSI Approved :: BSD License
Classifier: Operating System :: OS Independent
Classifier: Programming Language :: Python
Classifier: Topic :: Database :: Front-Ends
Classifier: Topic :: Scientific/Engineering
Classifier: Topic :: Software Development
License-File: LICENSE.rst
License-File: AUTHORS.rst
Requires-Dist: daff
Requires-Dist: networkx (>=2.4)
Requires-Dist: numpy
Requires-Dist: pandas
Requires-Dist: path.py
Requires-Dist: deepdiff
Requires-Dist: tqdm
